Metadata-Version: 2.1
Name: odoo14-addon-product_packaging_dimension
Version: 14.0.1.1.0
Summary: Manage packaging dimensions and weight
Home-page: https://github.com/OCA/product-attribute
Author: Camptocamp, Akretion, Odoo Community Association (OCA)
Author-email: support@odoo-community.org
License: AGPL-3
Classifier: Programming Language :: Python
Classifier: Framework :: Odoo
Classifier: Framework :: Odoo :: 14.0
Classifier: License :: OSI Approved :: GNU Affero General Public License v3
Requires-Python: >=3.6
Requires-Dist: odoo14-addon-product-logistics-uom
Requires-Dist: odoo<14.1dev,>=14.0a
